{
  "annotations": {
    "list": [
      {
        "builtIn": 1,
        "datasource": {
          "type": "grafana",
          "uid": "-- Grafana --"
        },
        "enable": true,
        "hide": true,
        "iconColor": "rgba(0, 211, 255, 1)",
        "name": "Annotations & Alerts",
        "type": "dashboard"
      }
    ]
  },
  "editable": true,
  "fiscalYearStartMonth": 0,
  "graphTooltip": 1,
  "id": null,
  "links": [],
  "liveNow": false,
  "panels": [
    {
      "datasource": {
        "type": "prometheus",
        "uid": "prometheus"
      },
      "description": "Storage capacity usage across media PVCs",
      "fieldConfig": {
        "defaults": {
          "color": {
            "mode": "thresholds"
          },
          "mappings": [],
          "max": 100,
          "min": 0,
          "thresholds": {
            "mode": "absolute",
            "steps": [
              {
                "color": "green",
                "value": null
              },
              {
                "color": "yellow",
                "value": 70
              },
              {
                "color": "red",
                "value": 90
              }
            ]
          },
          "unit": "percent"
        },
        "overrides": []
      },
      "gridPos": {
        "h": 8,
        "w": 8,
        "x": 0,
        "y": 0
      },
      "id": 1,
      "options": {
        "orientation": "auto",
        "reduceOptions": {
          "values": false,
          "calcs": [
            "lastNotNull"
          ],
          "fields": ""
        },
        "showThresholdLabels": false,
        "showThresholdMarkers": true
      },
      "pluginVersion": "10.0.0",
      "targets": [
        {
          "datasource": {
            "type": "prometheus",
            "uid": "prometheus"
          },
          "editorMode": "code",
          "expr": "(max(kubelet_volume_stats_used_bytes{namespace=\"media\",persistentvolumeclaim=\"media-tower-pvc\"}) / max(kubelet_volume_stats_capacity_bytes{namespace=\"media\",persistentvolumeclaim=\"media-tower-pvc\"})) * 100",
          "legendFormat": "Tower (NFS)",
          "range": true,
          "refId": "A"
        }
      ],
      "title": "Tower NFS Usage",
      "type": "gauge"
    },
    {
      "datasource": {
        "type": "prometheus",
        "uid": "prometheus"
      },
      "description": "Storage capacity usage for tower-2 NFS",
      "fieldConfig": {
        "defaults": {
          "color": {
            "mode": "thresholds"
          },
          "mappings": [],
          "max": 100,
          "min": 0,
          "thresholds": {
            "mode": "absolute",
            "steps": [
              {
                "color": "green",
                "value": null
              },
              {
                "color": "yellow",
                "value": 70
              },
              {
                "color": "red",
                "value": 90
              }
            ]
          },
          "unit": "percent"
        },
        "overrides": []
      },
      "gridPos": {
        "h": 8,
        "w": 8,
        "x": 8,
        "y": 0
      },
      "id": 2,
      "options": {
        "orientation": "auto",
        "reduceOptions": {
          "values": false,
          "calcs": [
            "lastNotNull"
          ],
          "fields": ""
        },
        "showThresholdLabels": false,
        "showThresholdMarkers": true
      },
      "pluginVersion": "10.0.0",
      "targets": [
        {
          "datasource": {
            "type": "prometheus",
            "uid": "prometheus"
          },
          "editorMode": "code",
          "expr": "(max(kubelet_volume_stats_used_bytes{namespace=\"media\",persistentvolumeclaim=\"media-tower-2-pvc\"}) / max(kubelet_volume_stats_capacity_bytes{namespace=\"media\",persistentvolumeclaim=\"media-tower-2-pvc\"})) * 100",
          "legendFormat": "Tower-2 (NFS)",
          "range": true,
          "refId": "A"
        }
      ],
      "title": "Tower-2 NFS Usage",
      "type": "gauge"
    },
    {
      "datasource": {
        "type": "prometheus",
        "uid": "prometheus"
      },
      "description": "Storage capacity usage for CephFS",
      "fieldConfig": {
        "defaults": {
          "color": {
            "mode": "thresholds"
          },
          "mappings": [],
          "max": 100,
          "min": 0,
          "thresholds": {
            "mode": "absolute",
            "steps": [
              {
                "color": "green",
                "value": null
              },
              {
                "color": "yellow",
                "value": 70
              },
              {
                "color": "red",
                "value": 90
              }
            ]
          },
          "unit": "percent"
        },
        "overrides": []
      },
      "gridPos": {
        "h": 8,
        "w": 8,
        "x": 16,
        "y": 0
      },
      "id": 3,
      "options": {
        "orientation": "auto",
        "reduceOptions": {
          "values": false,
          "calcs": [
            "lastNotNull"
          ],
          "fields": ""
        },
        "showThresholdLabels": false,
        "showThresholdMarkers": true
      },
      "pluginVersion": "10.0.0",
      "targets": [
        {
          "datasource": {
            "type": "prometheus",
            "uid": "prometheus"
          },
          "editorMode": "code",
          "expr": "(max(kubelet_volume_stats_used_bytes{namespace=\"media\",persistentvolumeclaim=\"media-cephfs-pvc\"}) / max(kubelet_volume_stats_capacity_bytes{namespace=\"media\",persistentvolumeclaim=\"media-cephfs-pvc\"})) * 100",
          "legendFormat": "CephFS",
          "range": true,
          "refId": "A"
        }
      ],
      "title": "CephFS Usage",
      "type": "gauge"
    },
    {
      "collapsed": false,
      "gridPos": {
        "h": 1,
        "w": 24,
        "x": 0,
        "y": 8
      },
      "id": 100,
      "panels": [],
      "title": "Migration Jobs",
      "type": "row"
    },
    {
      "datasource": {
        "type": "prometheus",
        "uid": "prometheus"
      },
      "description": "Number of active migration jobs",
      "fieldConfig": {
        "defaults": {
          "color": {
            "mode": "thresholds"
          },
          "mappings": [
            {
              "options": {
                "0": {
                  "color": "text",
                  "index": 0,
                  "text": "Idle"
                }
              },
              "type": "value"
            },
            {
              "options": {
                "from": 1,
                "result": {
                  "color": "blue",
                  "index": 1,
                  "text": "Active"
                },
                "to": 999
              },
              "type": "range"
            }
          ],
          "thresholds": {
            "mode": "absolute",
            "steps": [
              {
                "color": "text",
                "value": null
              },
              {
                "color": "blue",
                "value": 1
              }
            ]
          },
          "unit": "none"
        },
        "overrides": []
      },
      "gridPos": {
        "h": 4,
        "w": 4,
        "x": 0,
        "y": 9
      },
      "id": 10,
      "options": {
        "colorMode": "background",
        "graphMode": "none",
        "justifyMode": "auto",
        "orientation": "auto",
        "reduceOptions": {
          "values": false,
          "calcs": [
            "lastNotNull"
          ],
          "fields": ""
        },
        "textMode": "auto"
      },
      "pluginVersion": "10.0.0",
      "targets": [
        {
          "datasource": {
            "type": "prometheus",
            "uid": "prometheus"
          },
          "editorMode": "code",
          "expr": "count(kube_job_status_active{namespace=\"media\",job_name=~\"migrate.*\"} > 0) or vector(0)",
          "legendFormat": "Active Jobs",
          "range": true,
          "refId": "A"
        }
      ],
      "title": "Active Migration Jobs",
      "type": "stat"
    },
    {
      "datasource": {
        "type": "prometheus",
        "uid": "prometheus"
      },
      "description": "Number of completed migration jobs",
      "fieldConfig": {
        "defaults": {
          "color": {
            "mode": "thresholds"
          },
          "mappings": [],
          "thresholds": {
            "mode": "absolute",
            "steps": [
              {
                "color": "green",
                "value": null
              }
            ]
          },
          "unit": "none"
        },
        "overrides": []
      },
      "gridPos": {
        "h": 4,
        "w": 4,
        "x": 4,
        "y": 9
      },
      "id": 11,
      "options": {
        "colorMode": "value",
        "graphMode": "none",
        "justifyMode": "auto",
        "orientation": "auto",
        "reduceOptions": {
          "values": false,
          "calcs": [
            "lastNotNull"
          ],
          "fields": ""
        },
        "textMode": "auto"
      },
      "pluginVersion": "10.0.0",
      "targets": [
        {
          "datasource": {
            "type": "prometheus",
            "uid": "prometheus"
          },
          "editorMode": "code",
          "expr": "count(kube_job_status_succeeded{namespace=\"media\",job_name=~\"migrate.*\"} > 0) or vector(0)",
          "legendFormat": "Completed",
          "range": true,
          "refId": "A"
        }
      ],
      "title": "Completed Jobs",
      "type": "stat"
    },
    {
      "datasource": {
        "type": "prometheus",
        "uid": "prometheus"
      },
      "description": "Number of failed migration jobs",
      "fieldConfig": {
        "defaults": {
          "color": {
            "mode": "thresholds"
          },
          "mappings": [],
          "thresholds": {
            "mode": "absolute",
            "steps": [
              {
                "color": "green",
                "value": null
              },
              {
                "color": "red",
                "value": 1
              }
            ]
          },
          "unit": "none"
        },
        "overrides": []
      },
      "gridPos": {
        "h": 4,
        "w": 4,
        "x": 8,
        "y": 9
      },
      "id": 12,
      "options": {
        "colorMode": "value",
        "graphMode": "none",
        "justifyMode": "auto",
        "orientation": "auto",
        "reduceOptions": {
          "values": false,
          "calcs": [
            "lastNotNull"
          ],
          "fields": ""
        },
        "textMode": "auto"
      },
      "pluginVersion": "10.0.0",
      "targets": [
        {
          "datasource": {
            "type": "prometheus",
            "uid": "prometheus"
          },
          "editorMode": "code",
          "expr": "count(kube_job_status_failed{namespace=\"media\",job_name=~\"migrate.*\"} > 0) or vector(0)",
          "legendFormat": "Failed",
          "range": true,
          "refId": "A"
        }
      ],
      "title": "Failed Jobs",
      "type": "stat"
    },
    {
      "datasource": {
        "type": "prometheus",
        "uid": "prometheus"
      },
      "description": "CephFS write operations per second",
      "fieldConfig": {
        "defaults": {
          "color": {
            "mode": "palette-classic"
          },
          "custom": {
            "axisCenteredZero": false,
            "axisColorMode": "text",
            "axisLabel": "",
            "axisPlacement": "auto",
            "barAlignment": 0,
            "drawStyle": "line",
            "fillOpacity": 20,
            "gradientMode": "none",
            "hideFrom": {
              "tooltip": false,
              "viz": false,
              "legend": false
            },
            "lineInterpolation": "smooth",
            "lineWidth": 2,
            "pointSize": 5,
            "scaleDistribution": {
              "type": "linear"
            },
            "showPoints": "never",
            "spanNulls": false,
            "stacking": {
              "group": "A",
              "mode": "none"
            },
            "thresholdsStyle": {
              "mode": "off"
            }
          },
          "mappings": [],
          "thresholds": {
            "mode": "absolute",
            "steps": [
              {
                "color": "green",
                "value": null
              }
            ]
          },
          "unit": "ops"
        },
        "overrides": []
      },
      "gridPos": {
        "h": 4,
        "w": 12,
        "x": 12,
        "y": 9
      },
      "id": 13,
      "options": {
        "legend": {
          "calcs": [
            "last",
            "max"
          ],
          "displayMode": "list",
          "placement": "bottom",
          "showLegend": true
        },
        "tooltip": {
          "mode": "multi",
          "sort": "none"
        }
      },
      "targets": [
        {
          "datasource": {
            "type": "prometheus",
            "uid": "prometheus"
          },
          "editorMode": "code",
          "expr": "rate(ceph_pool_wr{name=\"cephfs-data\"}[5m])",
          "legendFormat": "CephFS Writes/sec",
          "range": true,
          "refId": "A"
        }
      ],
      "title": "CephFS Write Activity",
      "type": "timeseries"
    },
    {
      "datasource": {
        "type": "loki",
        "uid": "loki"
      },
      "description": "rsync transfer statistics from logs",
      "gridPos": {
        "h": 6,
        "w": 24,
        "x": 0,
        "y": 13
      },
      "id": 14,
      "options": {
        "dedupStrategy": "none",
        "enableLogDetails": true,
        "prettifyLogMessage": false,
        "showCommonLabels": false,
        "showLabels": false,
        "showTime": true,
        "sortOrder": "Descending",
        "wrapLogMessage": false
      },
      "targets": [
        {
          "datasource": {
            "type": "loki",
            "uid": "loki"
          },
          "editorMode": "code",
          "expr": "{namespace=\"media\", app_kubernetes_io_name=~\"migrate.*\"} |~ \"sent|received|speedup|total size\"",
          "queryType": "range",
          "refId": "A"
        }
      ],
      "title": "Migration Statistics (rsync output)",
      "type": "logs"
    },
    {
      "collapsed": false,
      "gridPos": {
        "h": 1,
        "w": 24,
        "x": 0,
        "y": 19
      },
      "id": 101,
      "panels": [],
      "title": "Storage Details",
      "type": "row"
    },
    {
      "datasource": {
        "type": "prometheus",
        "uid": "prometheus"
      },
      "description": "Total storage capacity and usage",
      "fieldConfig": {
        "defaults": {
          "color": {
            "mode": "palette-classic"
          },
          "custom": {
            "axisCenteredZero": false,
            "axisColorMode": "text",
            "axisLabel": "",
            "axisPlacement": "auto",
            "barAlignment": 0,
            "drawStyle": "line",
            "fillOpacity": 20,
            "gradientMode": "none",
            "hideFrom": {
              "tooltip": false,
              "viz": false,
              "legend": false
            },
            "lineInterpolation": "smooth",
            "lineWidth": 2,
            "pointSize": 5,
            "scaleDistribution": {
              "type": "linear"
            },
            "showPoints": "never",
            "spanNulls": false,
            "stacking": {
              "group": "A",
              "mode": "none"
            },
            "thresholdsStyle": {
              "mode": "off"
            }
          },
          "mappings": [],
          "thresholds": {
            "mode": "absolute",
            "steps": [
              {
                "color": "green",
                "value": null
              }
            ]
          },
          "unit": "decbytes"
        },
        "overrides": []
      },
      "gridPos": {
        "h": 8,
        "w": 24,
        "x": 0,
        "y": 20
      },
      "id": 4,
      "options": {
        "legend": {
          "calcs": [
            "last",
            "max"
          ],
          "displayMode": "table",
          "placement": "bottom",
          "showLegend": true
        },
        "tooltip": {
          "mode": "multi",
          "sort": "none"
        }
      },
      "targets": [
        {
          "datasource": {
            "type": "prometheus",
            "uid": "prometheus"
          },
          "editorMode": "code",
          "expr": "kubelet_volume_stats_used_bytes{namespace=\"media\",persistentvolumeclaim=~\"media-tower-pvc|media-tower-2-pvc|media-cephfs-pvc\"}",
          "legendFormat": "{{persistentvolumeclaim}} - Used",
          "range": true,
          "refId": "A"
        },
        {
          "datasource": {
            "type": "prometheus",
            "uid": "prometheus"
          },
          "editorMode": "code",
          "expr": "kubelet_volume_stats_capacity_bytes{namespace=\"media\",persistentvolumeclaim=~\"media-tower-pvc|media-tower-2-pvc|media-cephfs-pvc\"}",
          "legendFormat": "{{persistentvolumeclaim}} - Capacity",
          "range": true,
          "refId": "B"
        }
      ],
      "title": "Storage Capacity Over Time",
      "type": "timeseries"
    },
    {
      "datasource": {
        "type": "prometheus",
        "uid": "prometheus"
      },
      "description": "Number of inodes used vs available",
      "fieldConfig": {
        "defaults": {
          "color": {
            "mode": "thresholds"
          },
          "mappings": [],
          "thresholds": {
            "mode": "absolute",
            "steps": [
              {
                "color": "green",
                "value": null
              }
            ]
          },
          "unit": "short"
        },
        "overrides": []
      },
      "gridPos": {
        "h": 6,
        "w": 8,
        "x": 0,
        "y": 28
      },
      "id": 6,
      "options": {
        "colorMode": "value",
        "graphMode": "area",
        "justifyMode": "auto",
        "orientation": "auto",
        "reduceOptions": {
          "values": false,
          "calcs": [
            "lastNotNull"
          ],
          "fields": ""
        },
        "textMode": "auto"
      },
      "pluginVersion": "10.0.0",
      "targets": [
        {
          "datasource": {
            "type": "prometheus",
            "uid": "prometheus"
          },
          "editorMode": "code",
          "expr": "max(kubelet_volume_stats_inodes_used{namespace=\"media\",persistentvolumeclaim=\"media-tower-pvc\"})",
          "legendFormat": "Tower - Used",
          "range": true,
          "refId": "A"
        },
        {
          "datasource": {
            "type": "prometheus",
            "uid": "prometheus"
          },
          "editorMode": "code",
          "expr": "max(kubelet_volume_stats_inodes{namespace=\"media\",persistentvolumeclaim=\"media-tower-pvc\"})",
          "legendFormat": "Tower - Total",
          "range": true,
          "refId": "B"
        }
      ],
      "title": "Tower NFS Inodes",
      "type": "stat"
    },
    {
      "datasource": {
        "type": "prometheus",
        "uid": "prometheus"
      },
      "description": "Number of inodes used vs available",
      "fieldConfig": {
        "defaults": {
          "color": {
            "mode": "thresholds"
          },
          "mappings": [],
          "thresholds": {
            "mode": "absolute",
            "steps": [
              {
                "color": "green",
                "value": null
              }
            ]
          },
          "unit": "short"
        },
        "overrides": []
      },
      "gridPos": {
        "h": 6,
        "w": 8,
        "x": 8,
        "y": 28
      },
      "id": 7,
      "options": {
        "colorMode": "value",
        "graphMode": "area",
        "justifyMode": "auto",
        "orientation": "auto",
        "reduceOptions": {
          "values": false,
          "calcs": [
            "lastNotNull"
          ],
          "fields": ""
        },
        "textMode": "auto"
      },
      "pluginVersion": "10.0.0",
      "targets": [
        {
          "datasource": {
            "type": "prometheus",
            "uid": "prometheus"
          },
          "editorMode": "code",
          "expr": "max(kubelet_volume_stats_inodes_used{namespace=\"media\",persistentvolumeclaim=\"media-tower-2-pvc\"})",
          "legendFormat": "Tower-2 - Used",
          "range": true,
          "refId": "A"
        },
        {
          "datasource": {
            "type": "prometheus",
            "uid": "prometheus"
          },
          "editorMode": "code",
          "expr": "max(kubelet_volume_stats_inodes{namespace=\"media\",persistentvolumeclaim=\"media-tower-2-pvc\"})",
          "legendFormat": "Tower-2 - Total",
          "range": true,
          "refId": "B"
        }
      ],
      "title": "Tower-2 NFS Inodes",
      "type": "stat"
    },
    {
      "datasource": {
        "type": "prometheus",
        "uid": "prometheus"
      },
      "description": "Number of inodes used vs available",
      "fieldConfig": {
        "defaults": {
          "color": {
            "mode": "thresholds"
          },
          "mappings": [],
          "thresholds": {
            "mode": "absolute",
            "steps": [
              {
                "color": "green",
                "value": null
              }
            ]
          },
          "unit": "short"
        },
        "overrides": []
      },
      "gridPos": {
        "h": 6,
        "w": 8,
        "x": 16,
        "y": 28
      },
      "id": 8,
      "options": {
        "colorMode": "value",
        "graphMode": "area",
        "justifyMode": "auto",
        "orientation": "auto",
        "reduceOptions": {
          "values": false,
          "calcs": [
            "lastNotNull"
          ],
          "fields": ""
        },
        "textMode": "auto"
      },
      "pluginVersion": "10.0.0",
      "targets": [
        {
          "datasource": {
            "type": "prometheus",
            "uid": "prometheus"
          },
          "editorMode": "code",
          "expr": "max(kubelet_volume_stats_inodes_used{namespace=\"media\",persistentvolumeclaim=\"media-cephfs-pvc\"})",
          "legendFormat": "CephFS - Used",
          "range": true,
          "refId": "A"
        },
        {
          "datasource": {
            "type": "prometheus",
            "uid": "prometheus"
          },
          "editorMode": "code",
          "expr": "max(kubelet_volume_stats_inodes{namespace=\"media\",persistentvolumeclaim=\"media-cephfs-pvc\"})",
          "legendFormat": "CephFS - Total",
          "range": true,
          "refId": "B"
        }
      ],
      "title": "CephFS Inodes",
      "type": "stat"
    },
    {
      "datasource": {
        "type": "loki",
        "uid": "loki"
      },
      "description": "All migration job logs",
      "gridPos": {
        "h": 10,
        "w": 24,
        "x": 0,
        "y": 34
      },
      "id": 9,
      "options": {
        "dedupStrategy": "none",
        "enableLogDetails": true,
        "prettifyLogMessage": false,
        "showCommonLabels": false,
        "showLabels": false,
        "showTime": true,
        "sortOrder": "Descending",
        "wrapLogMessage": false
      },
      "targets": [
        {
          "datasource": {
            "type": "loki",
            "uid": "loki"
          },
          "editorMode": "code",
          "expr": "{namespace=\"media\", app_kubernetes_io_name=~\"migrate.*\"}",
          "queryType": "range",
          "refId": "A"
        }
      ],
      "title": "Full Migration Logs",
      "type": "logs"
    }
  ],
  "refresh": "30s",
  "schemaVersion": 38,
  "style": "dark",
  "tags": ["storage", "media", "ceph", "nfs", "migration"],
  "templating": {
    "list": []
  },
  "time": {
    "from": "now-6h",
    "to": "now"
  },
  "timepicker": {},
  "timezone": "",
  "title": "Media Storage",
  "uid": "media-storage",
  "version": 1,
  "weekStart": ""
}
